hiddenlib/README.md
hiddenlib/__init__.py
hiddenlib/search.py
hiddenlib/setup.py
hiddelib-1.0.0.dist-info/METADATA
hiddelib-1.0.0.dist-info/WHEEL
hiddelib-1.0.0.dist-info/top_level.txt
hiddelib-1.0.0.dist-info/RECORD
