Metadata-Version: 2.1
Name: hiddelib
Version: 1.0.0
Summary: hiddentool inc
Home-page: https://github.com/SuperZombi/Pypi-uploader
Author: agenthiddenoriginal
Author-email: tejajat421@joeroc.com
License: UNKNOWN
Platform: UNKNOWN
Classifier: Programming Language :: Python :: 3
Classifier: License :: OSI Approved :: MIT License
Classifier: Operating System :: OS Independent
Requires-Python: >=3.6
